README.rst
setup.py
usnparser/usn.py
usnparser.egg-info/PKG-INFO
usnparser.egg-info/SOURCES.txt
usnparser.egg-info/dependency_links.txt
usnparser.egg-info/top_level.txt