Metadata-Version: 1.1
Name: usnparser
Version: 4.1.2
Summary: A Python script to parse the NTFS USN journal
Home-page: https://github.com/PoorBillionaire/USN-Journal-Parser
Author: Adam Witt
Author-email: accidentalassist@gmail.com
License: Apache Software License
Platform: UNKNOWN
Classifier: Development Status :: 5 - Production/Stable
Classifier: Intended Audience :: Information Technology
Classifier: Topic :: Security
Classifier: License :: OSI Approved :: Apache Software License
